{ "dados" : [
      {"NO_MUNICIPIO":"Altinópolis","NO_UF":"São Paulo","SG_UF":"SP","CO_DISTRITO":350100405,"NO_ENTIDADE":"EMEI PROFESSORA EDINA DE PAULA HYSSA LUIZ","CO_ENTIDADE":35004332,"longitude":-47.391239,"latitude":-21.014019,"DEPENDENCIA":"Municipal","ATIVIDADE":"Em atividade","VÍNCULOS_PUBLICOS":"Secretaria de Educação","MANTENEDOR_ESCOLA_PRIVADA":"Empresa do setor privado","PREDIO_ESCOLAR":"Próprio","LOCAL_ESCOLAR":"Outros","ABASTECIMENTO_AGUA":"Rede pública","ABASTECIMENTO_ENERGIA":"Rede pública","TAXA_DE_ACESSIBILIDADE":1,"DS_ENDERECO":"ARISTOFON DE CASTRO ALVES","NU_ENDERECO":"240","DS_COMPLEMENTO":null,"NO_BAIRRO":"DISTRITO INDUSTRIAL","CO_CEP":14350000,"NU_DDD":16,"NU_TELEFONE":36659615,"ESGOTO":"Rede pública","TAXA_DE_INFRAESTRUTURA":0,"LISTA_INFRAESTRUTURAS":[],"LISTA_PROFISSIONAIS":[],"IDEB_2023":null}
,
{"NO_MUNICIPIO":"Altinópolis","NO_UF":"São Paulo","SG_UF":"SP","CO_DISTRITO":350100405,"NO_ENTIDADE":"ANTONIO BARREIROS PROFESSOR","CO_ENTIDADE":35022901,"longitude":-47.378448,"latitude":-21.020097,"DEPENDENCIA":"Estadual","ATIVIDADE":"Em atividade","VÍNCULOS_PUBLICOS":"Secretaria de Educação","MANTENEDOR_ESCOLA_PRIVADA":"Empresa do setor privado","PREDIO_ESCOLAR":"Próprio","LOCAL_ESCOLAR":"Salas em outra escola","ABASTECIMENTO_AGUA":"Rede pública","ABASTECIMENTO_ENERGIA":"Rede pública","TAXA_DE_ACESSIBILIDADE":0,"DS_ENDERECO":"PRACA JOAO MONTANS","NU_ENDERECO":"1","DS_COMPLEMENTO":"RUA","NO_BAIRRO":"GINASIO","CO_CEP":14350000,"NU_DDD":16,"NU_TELEFONE":36652397,"ESGOTO":"Rede pública","TAXA_DE_INFRAESTRUTURA":2,"LISTA_INFRAESTRUTURAS":["Laboratório de Informática","Quadra de Esportes"],"LISTA_PROFISSIONAIS":[],"IDEB_2023":"4,4"}
,
{"NO_MUNICIPIO":"Altinópolis","NO_UF":"São Paulo","SG_UF":"SP","CO_DISTRITO":350100405,"NO_ENTIDADE":"MONTEIRO LOBATO CENTRO COMUNITARIO EMEI","CO_ENTIDADE":35074536,"longitude":-47.366843,"latitude":-21.020493,"DEPENDENCIA":"Municipal","ATIVIDADE":"Em atividade","VÍNCULOS_PUBLICOS":"Secretaria de Educação","MANTENEDOR_ESCOLA_PRIVADA":"Empresa do setor privado","PREDIO_ESCOLAR":"Próprio","LOCAL_ESCOLAR":"Outros","ABASTECIMENTO_AGUA":"Rede pública","ABASTECIMENTO_ENERGIA":"Rede pública","TAXA_DE_ACESSIBILIDADE":0,"DS_ENDERECO":"RUA EDSON DUTRA BARROSO","NU_ENDERECO":"1230","DS_COMPLEMENTO":"RUA","NO_BAIRRO":"COHAB I","CO_CEP":14350000,"NU_DDD":16,"NU_TELEFONE":36659622,"ESGOTO":"Rede pública","TAXA_DE_INFRAESTRUTURA":0,"LISTA_INFRAESTRUTURAS":[],"LISTA_PROFISSIONAIS":["Segurança/Guarda"],"IDEB_2023":null}
,
{"NO_MUNICIPIO":"Altinópolis","NO_UF":"São Paulo","SG_UF":"SP","CO_DISTRITO":350100405,"NO_ENTIDADE":"CARLOS DRUMOND DE ANDRADE COLEGIO","CO_ENTIDADE":35124679,"longitude":null,"latitude":null,"DEPENDENCIA":"Privada","ATIVIDADE":"Em atividade","VÍNCULOS_PUBLICOS":"Não","MANTENEDOR_ESCOLA_PRIVADA":"Empresa do setor privado","PREDIO_ESCOLAR":"Próprio","LOCAL_ESCOLAR":"Outros","ABASTECIMENTO_AGUA":"Rede pública","ABASTECIMENTO_ENERGIA":"Rede pública","TAXA_DE_ACESSIBILIDADE":0,"DS_ENDERECO":"RUA MINAS GERAIS","NU_ENDERECO":"1050","DS_COMPLEMENTO":"RUA","NO_BAIRRO":"QUINTA DA BOA VISTA","CO_CEP":14350000,"NU_DDD":16,"NU_TELEFONE":36651111,"ESGOTO":"Rede pública","TAXA_DE_INFRAESTRUTURA":4,"LISTA_INFRAESTRUTURAS":["Biblioteca","Laboratório de Ciências","Laboratório de Informática","Quadra de Esportes"],"LISTA_PROFISSIONAIS":["Técnicos de apoio a tecnologias educacionais"],"IDEB_2023":null}
,
{"NO_MUNICIPIO":"Altinópolis","NO_UF":"São Paulo","SG_UF":"SP","CO_DISTRITO":350100405,"NO_ENTIDADE":"APAE DE ALTINOPOLIS CENTRO DE EDUCACAO ESPECIAL","CO_ENTIDADE":35149809,"longitude":null,"latitude":null,"DEPENDENCIA":"Privada","ATIVIDADE":"Em atividade","VÍNCULOS_PUBLICOS":"Não","MANTENEDOR_ESCOLA_PRIVADA":"Instituições sem fins lucrativos","PREDIO_ESCOLAR":"Próprio","LOCAL_ESCOLAR":"Outros","ABASTECIMENTO_AGUA":"Rede pública","ABASTECIMENTO_ENERGIA":"Rede pública","TAXA_DE_ACESSIBILIDADE":3,"DS_ENDERECO":"AVENIDA DA APAE","NU_ENDERECO":"550","DS_COMPLEMENTO":"RUA","NO_BAIRRO":"DISTRITO INDUSTRIAL","CO_CEP":14350000,"NU_DDD":16,"NU_TELEFONE":36650031,"ESGOTO":"Rede pública","TAXA_DE_INFRAESTRUTURA":2,"LISTA_INFRAESTRUTURAS":["Laboratório de Informática","Quadra de Esportes"],"LISTA_PROFISSIONAIS":["Fonoaudiólogo","Nutricionista","Psicólogo","Segurança/Guarda","Assistência Social"],"IDEB_2023":null}
,
{"NO_MUNICIPIO":"Altinópolis","NO_UF":"São Paulo","SG_UF":"SP","CO_DISTRITO":350100405,"NO_ENTIDADE":"DINAMICA ESCOLA","CO_ENTIDADE":35176459,"longitude":null,"latitude":null,"DEPENDENCIA":"Privada","ATIVIDADE":"Em atividade","VÍNCULOS_PUBLICOS":"Não","MANTENEDOR_ESCOLA_PRIVADA":"Empresa do setor privado","PREDIO_ESCOLAR":"Próprio","LOCAL_ESCOLAR":"Outros","ABASTECIMENTO_AGUA":"Rede pública","ABASTECIMENTO_ENERGIA":"Rede pública","TAXA_DE_ACESSIBILIDADE":0,"DS_ENDERECO":"RUA PARANA","NU_ENDERECO":"168","DS_COMPLEMENTO":"RUA","NO_BAIRRO":"GINASIO","CO_CEP":14350000,"NU_DDD":16,"NU_TELEFONE":36653055,"ESGOTO":"Rede pública","TAXA_DE_INFRAESTRUTURA":5,"LISTA_INFRAESTRUTURAS":["Biblioteca","Laboratório de Ciências","Laboratório de Informática","Quadra de Esportes","Sala de Ateliê de Artes"],"LISTA_PROFISSIONAIS":["Técnicos de apoio a tecnologias educacionais"],"IDEB_2023":null}
,
{"NO_MUNICIPIO":"Altinópolis","NO_UF":"São Paulo","SG_UF":"SP","CO_DISTRITO":350100405,"NO_ENTIDADE":"ALAYDE DE FIGUEIREDO PALMA CANASSA EMEFEI","CO_ENTIDADE":35210134,"longitude":-47.387353,"latitude":-21.018604,"DEPENDENCIA":"Municipal","ATIVIDADE":"Em atividade","VÍNCULOS_PUBLICOS":"Secretaria de Educação","MANTENEDOR_ESCOLA_PRIVADA":"Empresa do setor privado","PREDIO_ESCOLAR":"Próprio","LOCAL_ESCOLAR":"Outros","ABASTECIMENTO_AGUA":"Rede pública","ABASTECIMENTO_ENERGIA":"Rede pública","TAXA_DE_ACESSIBILIDADE":0,"DS_ENDERECO":"RUA ERNESTO MARCHIORI CAMPOS","NU_ENDERECO":"SN","DS_COMPLEMENTO":"RUA","NO_BAIRRO":"CECAP","CO_CEP":14350000,"NU_DDD":16,"NU_TELEFONE":36659589,"ESGOTO":"Rede pública","TAXA_DE_INFRAESTRUTURA":3,"LISTA_INFRAESTRUTURAS":["Biblioteca","Laboratório de Informática","Quadra de Esportes"],"LISTA_PROFISSIONAIS":["Técnicos de apoio a tecnologias educacionais"],"IDEB_2023":null}
,
{"NO_MUNICIPIO":"Altinópolis","NO_UF":"São Paulo","SG_UF":"SP","CO_DISTRITO":350100405,"NO_ENTIDADE":"EMIRENA VIEIRA DA FONSECA FIGUEIREDO EMEI","CO_ENTIDADE":35210146,"longitude":-47.383339,"latitude":-21.02176,"DEPENDENCIA":"Municipal","ATIVIDADE":"Em atividade","VÍNCULOS_PUBLICOS":"Secretaria de Educação","MANTENEDOR_ESCOLA_PRIVADA":"Empresa do setor privado","PREDIO_ESCOLAR":"Próprio","LOCAL_ESCOLAR":"Outros","ABASTECIMENTO_AGUA":"Rede pública","ABASTECIMENTO_ENERGIA":"Rede pública","TAXA_DE_ACESSIBILIDADE":0,"DS_ENDERECO":"MIGUEL HYSSA","NU_ENDERECO":"SN","DS_COMPLEMENTO":null,"NO_BAIRRO":"CDHU SILENO CRIVELENTI","CO_CEP":14350000,"NU_DDD":16,"NU_TELEFONE":36659620,"ESGOTO":"Rede pública","TAXA_DE_INFRAESTRUTURA":0,"LISTA_INFRAESTRUTURAS":[],"LISTA_PROFISSIONAIS":["Técnicos de apoio a tecnologias educacionais"],"IDEB_2023":null}
,
{"NO_MUNICIPIO":"Altinópolis","NO_UF":"São Paulo","SG_UF":"SP","CO_DISTRITO":350100405,"NO_ENTIDADE":"MIGUEL ANGELO SABIA EMEFEI","CO_ENTIDADE":35210158,"longitude":null,"latitude":null,"DEPENDENCIA":"Municipal","ATIVIDADE":"Paralisada","VÍNCULOS_PUBLICOS":"Não","MANTENEDOR_ESCOLA_PRIVADA":"Empresa do setor privado","PREDIO_ESCOLAR":"Indefinido","LOCAL_ESCOLAR":"Outros","ABASTECIMENTO_AGUA":"Não há abastecimento de água","ABASTECIMENTO_ENERGIA":"Não há energia elétrica","TAXA_DE_ACESSIBILIDADE":0,"DS_ENDERECO":"AVENIDA CORONEL ANTONIO JUSTINO DE FIGUEIREDO","NU_ENDERECO":"SN","DS_COMPLEMENTO":"RUA","NO_BAIRRO":"JARDIM ESPLANADA","CO_CEP":14350000,"NU_DDD":16,"NU_TELEFONE":36659580,"ESGOTO":"Não há tratamento de esgoto","TAXA_DE_INFRAESTRUTURA":0,"LISTA_INFRAESTRUTURAS":[],"LISTA_PROFISSIONAIS":[],"IDEB_2023":null}
,
{"NO_MUNICIPIO":"Altinópolis","NO_UF":"São Paulo","SG_UF":"SP","CO_DISTRITO":350100405,"NO_ENTIDADE":"CARMEM MIGUEL VICARI EMEF","CO_ENTIDADE":35220899,"longitude":-47.429555,"latitude":-21.019408,"DEPENDENCIA":"Municipal","ATIVIDADE":"Em atividade","VÍNCULOS_PUBLICOS":"Secretaria de Educação","MANTENEDOR_ESCOLA_PRIVADA":"Empresa do setor privado","PREDIO_ESCOLAR":"Cedido","LOCAL_ESCOLAR":"Outros","ABASTECIMENTO_AGUA":"Poço artesiano","ABASTECIMENTO_ENERGIA":"Rede pública","TAXA_DE_ACESSIBILIDADE":0,"DS_ENDERECO":"RODOVIA ALTINO ARANTES","NU_ENDERECO":"KM 31","DS_COMPLEMENTO":"RUA","NO_BAIRRO":"FAZENDA CASCATA","CO_CEP":14350000,"NU_DDD":16,"NU_TELEFONE":36659588,"ESGOTO":"Fossa Séptica","TAXA_DE_INFRAESTRUTURA":4,"LISTA_INFRAESTRUTURAS":["Biblioteca","Laboratório de Informática","Piscina","Quadra de Esportes"],"LISTA_PROFISSIONAIS":["Segurança/Guarda","Técnicos de apoio a tecnologias educacionais"],"IDEB_2023":null}
,
{"NO_MUNICIPIO":"Altinópolis","NO_UF":"São Paulo","SG_UF":"SP","CO_DISTRITO":350100405,"NO_ENTIDADE":"GERALDO TROSSEL PADRE EMEF","CO_ENTIDADE":35220905,"longitude":-47.374611,"latitude":-21.019953,"DEPENDENCIA":"Municipal","ATIVIDADE":"Em atividade","VÍNCULOS_PUBLICOS":"Secretaria de Educação","MANTENEDOR_ESCOLA_PRIVADA":"Empresa do setor privado","PREDIO_ESCOLAR":"Cedido","LOCAL_ESCOLAR":"Outros","ABASTECIMENTO_AGUA":"Rede pública","ABASTECIMENTO_ENERGIA":"Rede pública","TAXA_DE_ACESSIBILIDADE":0,"DS_ENDERECO":"RUA ALAGOAS","NU_ENDERECO":"248","DS_COMPLEMENTO":"RUA","NO_BAIRRO":"VILA MARIA","CO_CEP":14350000,"NU_DDD":16,"NU_TELEFONE":36659587,"ESGOTO":"Rede pública","TAXA_DE_INFRAESTRUTURA":2,"LISTA_INFRAESTRUTURAS":["Laboratório de Informática","Quadra de Esportes"],"LISTA_PROFISSIONAIS":["Nutricionista","Segurança/Guarda"],"IDEB_2023":null}
,
{"NO_MUNICIPIO":"Altinópolis","NO_UF":"São Paulo","SG_UF":"SP","CO_DISTRITO":350100405,"NO_ENTIDADE":"JOAQUIM DA CUNHA CORONEL EMEF","CO_ENTIDADE":35239781,"longitude":-47.37201,"latitude":-21.026633,"DEPENDENCIA":"Municipal","ATIVIDADE":"Em atividade","VÍNCULOS_PUBLICOS":"Secretaria de Educação","MANTENEDOR_ESCOLA_PRIVADA":"Empresa do setor privado","PREDIO_ESCOLAR":"Cedido","LOCAL_ESCOLAR":"Outros","ABASTECIMENTO_AGUA":"Rede pública","ABASTECIMENTO_ENERGIA":"Rede pública","TAXA_DE_ACESSIBILIDADE":3,"DS_ENDERECO":"RUA CARLOS GOMES","NU_ENDERECO":"170","DS_COMPLEMENTO":"RUA","NO_BAIRRO":"CENTRO","CO_CEP":14350000,"NU_DDD":16,"NU_TELEFONE":36659585,"ESGOTO":"Rede pública","TAXA_DE_INFRAESTRUTURA":5,"LISTA_INFRAESTRUTURAS":["Área Verde","Biblioteca","Laboratório de Ciências","Laboratório de Informática","Quadra de Esportes"],"LISTA_PROFISSIONAIS":["Segurança/Guarda","Técnicos de apoio a tecnologias educacionais","Assistência Social"],"IDEB_2023":null}
,
{"NO_MUNICIPIO":"Altinópolis","NO_UF":"São Paulo","SG_UF":"SP","CO_DISTRITO":350100405,"NO_ENTIDADE":"ERMELINDA ROSALINA SAMMARCO DE FIGUEIREDO EMEFEI","CO_ENTIDADE":35281360,"longitude":-47.38123,"latitude":-21.024843,"DEPENDENCIA":"Municipal","ATIVIDADE":"Em atividade","VÍNCULOS_PUBLICOS":"Secretaria de Educação","MANTENEDOR_ESCOLA_PRIVADA":"Empresa do setor privado","PREDIO_ESCOLAR":"Próprio","LOCAL_ESCOLAR":"Outros","ABASTECIMENTO_AGUA":"Rede pública","ABASTECIMENTO_ENERGIA":"Rede pública","TAXA_DE_ACESSIBILIDADE":3,"DS_ENDERECO":"RUA JOAQUIM PAULINO SOUZA","NU_ENDERECO":"145","DS_COMPLEMENTO":"RUA","NO_BAIRRO":"SALIM ANTONIO CALIL","CO_CEP":14350000,"NU_DDD":16,"NU_TELEFONE":36659586,"ESGOTO":"Rede pública","TAXA_DE_INFRAESTRUTURA":0,"LISTA_INFRAESTRUTURAS":[],"LISTA_PROFISSIONAIS":["Segurança/Guarda"],"IDEB_2023":null}
,
{"NO_MUNICIPIO":"Altinópolis","NO_UF":"São Paulo","SG_UF":"SP","CO_DISTRITO":350100405,"NO_ENTIDADE":"JUCA LOURENCO DE CASTRO EMEI","CO_ENTIDADE":35471461,"longitude":null,"latitude":null,"DEPENDENCIA":"Municipal","ATIVIDADE":"Paralisada","VÍNCULOS_PUBLICOS":"Não","MANTENEDOR_ESCOLA_PRIVADA":"Empresa do setor privado","PREDIO_ESCOLAR":"Indefinido","LOCAL_ESCOLAR":"Outros","ABASTECIMENTO_AGUA":"Não há abastecimento de água","ABASTECIMENTO_ENERGIA":"Não há energia elétrica","TAXA_DE_ACESSIBILIDADE":0,"DS_ENDERECO":"FAZENDA BELA VISTA","NU_ENDERECO":"SN","DS_COMPLEMENTO":"RUA","NO_BAIRRO":"BELA VISTA","CO_CEP":14350000,"NU_DDD":16,"NU_TELEFONE":36659609,"ESGOTO":"Não há tratamento de esgoto","TAXA_DE_INFRAESTRUTURA":0,"LISTA_INFRAESTRUTURAS":[],"LISTA_PROFISSIONAIS":[],"IDEB_2023":null}
,
{"NO_MUNICIPIO":"Altinópolis","NO_UF":"São Paulo","SG_UF":"SP","CO_DISTRITO":350100405,"NO_ENTIDADE":"ANA LUCIA FELIPE PENTEADO FERREIRA EMEFEI","CO_ENTIDADE":35567644,"longitude":-47.401006,"latitude":-21.019902,"DEPENDENCIA":"Municipal","ATIVIDADE":"Paralisada","VÍNCULOS_PUBLICOS":"Não","MANTENEDOR_ESCOLA_PRIVADA":"Empresa do setor privado","PREDIO_ESCOLAR":"Indefinido","LOCAL_ESCOLAR":"Outros","ABASTECIMENTO_AGUA":"Não há abastecimento de água","ABASTECIMENTO_ENERGIA":"Não há energia elétrica","TAXA_DE_ACESSIBILIDADE":0,"DS_ENDERECO":"RUA EMERSON DE LIMA FIGUEIREDO","NU_ENDERECO":"275","DS_COMPLEMENTO":"RUA","NO_BAIRRO":"FIGUEIREDO WALTER","CO_CEP":14350000,"NU_DDD":16,"NU_TELEFONE":36659621,"ESGOTO":"Não há tratamento de esgoto","TAXA_DE_INFRAESTRUTURA":0,"LISTA_INFRAESTRUTURAS":[],"LISTA_PROFISSIONAIS":[],"IDEB_2023":null}
,
{"NO_MUNICIPIO":"Altinópolis","NO_UF":"São Paulo","SG_UF":"SP","CO_DISTRITO":350100405,"NO_ENTIDADE":"PARQUE DE EXPOSICAO STA CRUZ CENTRO DE A PEDAGOGICO","CO_ENTIDADE":35567668,"longitude":-47.401492,"latitude":-21.014774,"DEPENDENCIA":"Municipal","ATIVIDADE":"Paralisada","VÍNCULOS_PUBLICOS":"Não","MANTENEDOR_ESCOLA_PRIVADA":"Empresa do setor privado","PREDIO_ESCOLAR":"Indefinido","LOCAL_ESCOLAR":"Outros","ABASTECIMENTO_AGUA":"Não há abastecimento de água","ABASTECIMENTO_ENERGIA":"Não há energia elétrica","TAXA_DE_ACESSIBILIDADE":0,"DS_ENDERECO":"ESTRADA JOSE LEME WALTER","NU_ENDERECO":"SN","DS_COMPLEMENTO":"RUA","NO_BAIRRO":"BAIRRO EXPOAL","CO_CEP":14350000,"NU_DDD":16,"NU_TELEFONE":36659580,"ESGOTO":"Não há tratamento de esgoto","TAXA_DE_INFRAESTRUTURA":0,"LISTA_INFRAESTRUTURAS":[],"LISTA_PROFISSIONAIS":[],"IDEB_2023":null}
,
{"NO_MUNICIPIO":"Altinópolis","NO_UF":"São Paulo","SG_UF":"SP","CO_DISTRITO":350100405,"NO_ENTIDADE":"EMEI PROFESSORA AMARILIS CALIL JARDIM","CO_ENTIDADE":35585270,"longitude":-47.404627,"latitude":-21.018263,"DEPENDENCIA":"Municipal","ATIVIDADE":"Em atividade","VÍNCULOS_PUBLICOS":"Secretaria de Educação","MANTENEDOR_ESCOLA_PRIVADA":"Empresa do setor privado","PREDIO_ESCOLAR":"Próprio","LOCAL_ESCOLAR":"Outros","ABASTECIMENTO_AGUA":"Rede pública","ABASTECIMENTO_ENERGIA":"Rede pública","TAXA_DE_ACESSIBILIDADE":0,"DS_ENDERECO":"RUA 5","NU_ENDERECO":"500","DS_COMPLEMENTO":"RUA","NO_BAIRRO":"EDMAR VICENTINI","CO_CEP":14350000,"NU_DDD":16,"NU_TELEFONE":36659630,"ESGOTO":"Rede pública","TAXA_DE_INFRAESTRUTURA":0,"LISTA_INFRAESTRUTURAS":[],"LISTA_PROFISSIONAIS":["Segurança/Guarda","Técnicos de apoio a tecnologias educacionais"],"IDEB_2023":null}
,
{"NO_MUNICIPIO":"Altinópolis","NO_UF":"São Paulo","SG_UF":"SP","CO_DISTRITO":350100405,"NO_ENTIDADE":"GABRIELA DOS REIS EMEI R","CO_ENTIDADE":35664765,"longitude":null,"latitude":null,"DEPENDENCIA":"Municipal","ATIVIDADE":"Paralisada","VÍNCULOS_PUBLICOS":"Não","MANTENEDOR_ESCOLA_PRIVADA":"Empresa do setor privado","PREDIO_ESCOLAR":"Indefinido","LOCAL_ESCOLAR":"Outros","ABASTECIMENTO_AGUA":"Não há abastecimento de água","ABASTECIMENTO_ENERGIA":"Não há energia elétrica","TAXA_DE_ACESSIBILIDADE":0,"DS_ENDERECO":"BAIRRO MONJOLINHO","NU_ENDERECO":"SN","DS_COMPLEMENTO":"RUA","NO_BAIRRO":"CENTRO","CO_CEP":14350000,"NU_DDD":16,"NU_TELEFONE":36653615,"ESGOTO":"Não há tratamento de esgoto","TAXA_DE_INFRAESTRUTURA":0,"LISTA_INFRAESTRUTURAS":[],"LISTA_PROFISSIONAIS":[],"IDEB_2023":null}
 ] }