{ "dados" : [
      {"NO_MUNICIPIO":"Ipiguá","NO_UF":"São Paulo","SG_UF":"SP","CO_DISTRITO":352115005,"NO_ENTIDADE":"FRANCISCO PURITA PROFESSOR","CO_ENTIDADE":35028617,"longitude":-49.385959,"latitude":-20.655924,"DEPENDENCIA":"Estadual","ATIVIDADE":"Em atividade","VÍNCULOS_PUBLICOS":"Secretaria de Educação","MANTENEDOR_ESCOLA_PRIVADA":"Empresa do setor privado","PREDIO_ESCOLAR":"Próprio","LOCAL_ESCOLAR":"Outros","ABASTECIMENTO_AGUA":"Rede pública","ABASTECIMENTO_ENERGIA":"Rede pública","TAXA_DE_ACESSIBILIDADE":3,"DS_ENDERECO":"RUA DO ROSARIO","NU_ENDERECO":"118","DS_COMPLEMENTO":"RUA","NO_BAIRRO":"CENTRO","CO_CEP":15108000,"NU_DDD":17,"NU_TELEFONE":32691221,"ESGOTO":"Rede pública","TAXA_DE_INFRAESTRUTURA":3,"LISTA_INFRAESTRUTURAS":["Laboratório de Ciências","Laboratório de Informática","Quadra de Esportes"],"LISTA_PROFISSIONAIS":["Psicólogo","Técnicos de apoio a tecnologias educacionais"],"IDEB_2023":"4,5"}
,
{"NO_MUNICIPIO":"Ipiguá","NO_UF":"São Paulo","SG_UF":"SP","CO_DISTRITO":352115005,"NO_ENTIDADE":"HENRIQUE PEREIRA DOS SANTOS EMEI","CO_ENTIDADE":35064695,"longitude":-49.387148,"latitude":-20.654056,"DEPENDENCIA":"Municipal","ATIVIDADE":"Em atividade","VÍNCULOS_PUBLICOS":"Secretaria de Educação","MANTENEDOR_ESCOLA_PRIVADA":"Empresa do setor privado","PREDIO_ESCOLAR":"Próprio","LOCAL_ESCOLAR":"Outros","ABASTECIMENTO_AGUA":"Rede pública","ABASTECIMENTO_ENERGIA":"Rede pública","TAXA_DE_ACESSIBILIDADE":0,"DS_ENDERECO":"RUA PAULO BARBOSA","NU_ENDERECO":"210","DS_COMPLEMENTO":"RUA","NO_BAIRRO":"CENTRO","CO_CEP":15108000,"NU_DDD":17,"NU_TELEFONE":32699004,"ESGOTO":"Rede pública","TAXA_DE_INFRAESTRUTURA":0,"LISTA_INFRAESTRUTURAS":[],"LISTA_PROFISSIONAIS":["Nutricionista"],"IDEB_2023":null}
,
{"NO_MUNICIPIO":"Ipiguá","NO_UF":"São Paulo","SG_UF":"SP","CO_DISTRITO":352115005,"NO_ENTIDADE":"LUCIMARA PAZIANOTO PROFA EMEF","CO_ENTIDADE":35245318,"longitude":-49.385306,"latitude":-20.654943,"DEPENDENCIA":"Municipal","ATIVIDADE":"Em atividade","VÍNCULOS_PUBLICOS":"Secretaria de Educação","MANTENEDOR_ESCOLA_PRIVADA":"Empresa do setor privado","PREDIO_ESCOLAR":"Próprio","LOCAL_ESCOLAR":"Outros","ABASTECIMENTO_AGUA":"Rede pública","ABASTECIMENTO_ENERGIA":"Rede pública","TAXA_DE_ACESSIBILIDADE":3,"DS_ENDERECO":"RUA ARAGUARI","NU_ENDERECO":"70","DS_COMPLEMENTO":"RUA","NO_BAIRRO":"JARDIM PRIMAVERA","CO_CEP":15108000,"NU_DDD":17,"NU_TELEFONE":32699017,"ESGOTO":"Rede pública","TAXA_DE_INFRAESTRUTURA":0,"LISTA_INFRAESTRUTURAS":[],"LISTA_PROFISSIONAIS":["Nutricionista"],"IDEB_2023":null}
 ] }