{ "dados" : [
      {"NO_MUNICIPIO":"Igaraçu do Tietê","NO_UF":"São Paulo","SG_UF":"SP","CO_DISTRITO":352000405,"NO_ENTIDADE":"CASA DA CRIANCA DE IGARACU DO TIETE","CO_ENTIDADE":35007477,"longitude":null,"latitude":null,"DEPENDENCIA":"Privada","ATIVIDADE":"Paralisada","VÍNCULOS_PUBLICOS":"Não","MANTENEDOR_ESCOLA_PRIVADA":"Empresa do setor privado","PREDIO_ESCOLAR":"Indefinido","LOCAL_ESCOLAR":"Outros","ABASTECIMENTO_AGUA":"Não há abastecimento de água","ABASTECIMENTO_ENERGIA":"Não há energia elétrica","TAXA_DE_ACESSIBILIDADE":0,"DS_ENDERECO":"RUA DOM CARLOS","NU_ENDERECO":"323","DS_COMPLEMENTO":null,"NO_BAIRRO":"CENTRO","CO_CEP":17350033,"NU_DDD":14,"NU_TELEFONE":36441536,"ESGOTO":"Não há tratamento de esgoto","TAXA_DE_INFRAESTRUTURA":0,"LISTA_INFRAESTRUTURAS":[],"LISTA_PROFISSIONAIS":[],"IDEB_2023":null}
,
{"NO_MUNICIPIO":"Igaraçu do Tietê","NO_UF":"São Paulo","SG_UF":"SP","CO_DISTRITO":352000405,"NO_ENTIDADE":"CEMEI TICA VARRASCHIN ANTONIA VARRASCHIN LEITE DE PAULA","CO_ENTIDADE":35007601,"longitude":null,"latitude":null,"DEPENDENCIA":"Municipal","ATIVIDADE":"Em atividade","VÍNCULOS_PUBLICOS":"Secretaria de Educação","MANTENEDOR_ESCOLA_PRIVADA":"Empresa do setor privado","PREDIO_ESCOLAR":"Próprio","LOCAL_ESCOLAR":"Outros","ABASTECIMENTO_AGUA":"Rede pública","ABASTECIMENTO_ENERGIA":"Rede pública","TAXA_DE_ACESSIBILIDADE":0,"DS_ENDERECO":"RUA MIGUEL GOMES","NU_ENDERECO":"187","DS_COMPLEMENTO":null,"NO_BAIRRO":"JARDIM DOS ANTURIOS","CO_CEP":17352504,"NU_DDD":14,"NU_TELEFONE":36444499,"ESGOTO":"Rede pública","TAXA_DE_INFRAESTRUTURA":0,"LISTA_INFRAESTRUTURAS":[],"LISTA_PROFISSIONAIS":[],"IDEB_2023":null}
,
{"NO_MUNICIPIO":"Igaraçu do Tietê","NO_UF":"São Paulo","SG_UF":"SP","CO_DISTRITO":352000405,"NO_ENTIDADE":"FAZENDA VISTA ALEGRE","CO_ENTIDADE":35009554,"longitude":null,"latitude":null,"DEPENDENCIA":"Estadual","ATIVIDADE":"Em atividade","VÍNCULOS_PUBLICOS":"Secretaria de Educação","MANTENEDOR_ESCOLA_PRIVADA":"Empresa do setor privado","PREDIO_ESCOLAR":"Próprio","LOCAL_ESCOLAR":"Outros","ABASTECIMENTO_AGUA":"Rede pública","ABASTECIMENTO_ENERGIA":"Rede pública","TAXA_DE_ACESSIBILIDADE":5,"DS_ENDERECO":"RUA MARIA SALVE FERRAZ","NU_ENDERECO":"30","DS_COMPLEMENTO":null,"NO_BAIRRO":"CONJUNTO HABITACIONAL ALFREDO FERNANDES","CO_CEP":17354120,"NU_DDD":14,"NU_TELEFONE":36443006,"ESGOTO":"Rede pública","TAXA_DE_INFRAESTRUTURA":4,"LISTA_INFRAESTRUTURAS":["Área Verde","Laboratório de Ciências","Laboratório de Informática","Quadra de Esportes"],"LISTA_PROFISSIONAIS":[],"IDEB_2023":null}
,
{"NO_MUNICIPIO":"Igaraçu do Tietê","NO_UF":"São Paulo","SG_UF":"SP","CO_DISTRITO":352000405,"NO_ENTIDADE":"JOSE CONTI","CO_ENTIDADE":35025963,"longitude":-48.56242,"latitude":-22.510167,"DEPENDENCIA":"Estadual","ATIVIDADE":"Em atividade","VÍNCULOS_PUBLICOS":"Secretaria de Educação","MANTENEDOR_ESCOLA_PRIVADA":"Empresa do setor privado","PREDIO_ESCOLAR":"Próprio","LOCAL_ESCOLAR":"Prédio compartilhado com outra escola","ABASTECIMENTO_AGUA":"Rede pública","ABASTECIMENTO_ENERGIA":"Rede pública","TAXA_DE_ACESSIBILIDADE":7,"DS_ENDERECO":"AVENIDA JOSE MICHEL MUCARE","NU_ENDERECO":"801","DS_COMPLEMENTO":null,"NO_BAIRRO":"VILA BOA VISTA","CO_CEP":17350298,"NU_DDD":14,"NU_TELEFONE":36441777,"ESGOTO":"Rede pública","TAXA_DE_INFRAESTRUTURA":3,"LISTA_INFRAESTRUTURAS":["Biblioteca","Laboratório de Informática","Quadra de Esportes"],"LISTA_PROFISSIONAIS":[],"IDEB_2023":"-"}
,
{"NO_MUNICIPIO":"Igaraçu do Tietê","NO_UF":"São Paulo","SG_UF":"SP","CO_DISTRITO":352000405,"NO_ENTIDADE":"ANGELO DOMEZI PREFEITO","CO_ENTIDADE":35044052,"longitude":null,"latitude":null,"DEPENDENCIA":"Estadual","ATIVIDADE":"Paralisada","VÍNCULOS_PUBLICOS":"Não","MANTENEDOR_ESCOLA_PRIVADA":"Empresa do setor privado","PREDIO_ESCOLAR":"Indefinido","LOCAL_ESCOLAR":"Outros","ABASTECIMENTO_AGUA":"Não há abastecimento de água","ABASTECIMENTO_ENERGIA":"Não há energia elétrica","TAXA_DE_ACESSIBILIDADE":0,"DS_ENDERECO":"RUA JULIO VIEIRA","NU_ENDERECO":"395","DS_COMPLEMENTO":"RUA","NO_BAIRRO":"CENTRO","CO_CEP":17350017,"NU_DDD":14,"NU_TELEFONE":36441666,"ESGOTO":"Não há tratamento de esgoto","TAXA_DE_INFRAESTRUTURA":0,"LISTA_INFRAESTRUTURAS":[],"LISTA_PROFISSIONAIS":[],"IDEB_2023":null}
,
{"NO_MUNICIPIO":"Igaraçu do Tietê","NO_UF":"São Paulo","SG_UF":"SP","CO_DISTRITO":352000405,"NO_ENTIDADE":"JOSE SAHADE PREFEITO EM","CO_ENTIDADE":35064026,"longitude":-48.566417,"latitude":-22.524745,"DEPENDENCIA":"Municipal","ATIVIDADE":"Em atividade","VÍNCULOS_PUBLICOS":"Secretaria de Educação","MANTENEDOR_ESCOLA_PRIVADA":"Empresa do setor privado","PREDIO_ESCOLAR":"Próprio","LOCAL_ESCOLAR":"Outros","ABASTECIMENTO_AGUA":"Rede pública","ABASTECIMENTO_ENERGIA":"Rede pública","TAXA_DE_ACESSIBILIDADE":2,"DS_ENDERECO":"RUA VIRGILIO TUSCHI","NU_ENDERECO":"200","DS_COMPLEMENTO":null,"NO_BAIRRO":"COHAB","CO_CEP":17354138,"NU_DDD":14,"NU_TELEFONE":36445277,"ESGOTO":"Rede pública","TAXA_DE_INFRAESTRUTURA":1,"LISTA_INFRAESTRUTURAS":["Quadra de Esportes"],"LISTA_PROFISSIONAIS":[],"IDEB_2023":null}
,
{"NO_MUNICIPIO":"Igaraçu do Tietê","NO_UF":"São Paulo","SG_UF":"SP","CO_DISTRITO":352000405,"NO_ENTIDADE":"MARIA CARMEN TAVANO DOMEZI EMEIEF","CO_ENTIDADE":35092095,"longitude":-48.552085,"latitude":-22.508146,"DEPENDENCIA":"Municipal","ATIVIDADE":"Em atividade","VÍNCULOS_PUBLICOS":"Secretaria de Educação","MANTENEDOR_ESCOLA_PRIVADA":"Empresa do setor privado","PREDIO_ESCOLAR":"Próprio","LOCAL_ESCOLAR":"Outros","ABASTECIMENTO_AGUA":"Rede pública","ABASTECIMENTO_ENERGIA":"Rede pública","TAXA_DE_ACESSIBILIDADE":0,"DS_ENDERECO":"PRACA PROFESSORA AUGUSTA CARVALHO","NU_ENDERECO":"SN","DS_COMPLEMENTO":null,"NO_BAIRRO":"VILA NOSSA SENHORA APARECIDA","CO_CEP":17350122,"NU_DDD":14,"NU_TELEFONE":36441255,"ESGOTO":"Rede pública","TAXA_DE_INFRAESTRUTURA":2,"LISTA_INFRAESTRUTURAS":["Laboratório de Informática","Quadra de Esportes"],"LISTA_PROFISSIONAIS":[],"IDEB_2023":null}
,
{"NO_MUNICIPIO":"Igaraçu do Tietê","NO_UF":"São Paulo","SG_UF":"SP","CO_DISTRITO":352000405,"NO_ENTIDADE":"SESI 272 CENTRO EDUCACIONAL","CO_ENTIDADE":35115859,"longitude":null,"latitude":null,"DEPENDENCIA":"Privada","ATIVIDADE":"Em atividade","VÍNCULOS_PUBLICOS":"Não","MANTENEDOR_ESCOLA_PRIVADA":"Sistema S (Sesi, Senai, Sesc, outros)","PREDIO_ESCOLAR":"Próprio","LOCAL_ESCOLAR":"Outros","ABASTECIMENTO_AGUA":"Rede pública","ABASTECIMENTO_ENERGIA":"Rede pública","TAXA_DE_ACESSIBILIDADE":2,"DS_ENDERECO":"RUA JUSTINO DE LUCCI","NU_ENDERECO":"234","DS_COMPLEMENTO":"BAIRRO RESIDENCIAL S","NO_BAIRRO":"RESIDENCIAL SAO JOSE","CO_CEP":17352186,"NU_DDD":14,"NU_TELEFONE":36441700,"ESGOTO":"Rede pública","TAXA_DE_INFRAESTRUTURA":5,"LISTA_INFRAESTRUTURAS":["Área Verde","Biblioteca","Laboratório de Ciências","Laboratório de Informática","Quadra de Esportes"],"LISTA_PROFISSIONAIS":["Nutricionista","Segurança/Guarda"],"IDEB_2023":"-"}
,
{"NO_MUNICIPIO":"Igaraçu do Tietê","NO_UF":"São Paulo","SG_UF":"SP","CO_DISTRITO":352000405,"NO_ENTIDADE":"APAE DE IGARACU DO TIETE","CO_ENTIDADE":35145762,"longitude":null,"latitude":null,"DEPENDENCIA":"Privada","ATIVIDADE":"Em atividade","VÍNCULOS_PUBLICOS":"Não","MANTENEDOR_ESCOLA_PRIVADA":"Instituições sem fins lucrativos","PREDIO_ESCOLAR":"Cedido","LOCAL_ESCOLAR":"Outros","ABASTECIMENTO_AGUA":"Rede pública","ABASTECIMENTO_ENERGIA":"Rede pública","TAXA_DE_ACESSIBILIDADE":2,"DS_ENDERECO":"RUA PEDRO BIAZOTTO","NU_ENDERECO":"383","DS_COMPLEMENTO":null,"NO_BAIRRO":"VILA LEOZINA","CO_CEP":17352112,"NU_DDD":14,"NU_TELEFONE":36441021,"ESGOTO":"Rede pública","TAXA_DE_INFRAESTRUTURA":0,"LISTA_INFRAESTRUTURAS":[],"LISTA_PROFISSIONAIS":["Fonoaudiólogo","Psicólogo","Técnicos de apoio a tecnologias educacionais","Assistência Social"],"IDEB_2023":null}
,
{"NO_MUNICIPIO":"Igaraçu do Tietê","NO_UF":"São Paulo","SG_UF":"SP","CO_DISTRITO":352000405,"NO_ENTIDADE":"COLEGIO SABER","CO_ENTIDADE":35179802,"longitude":null,"latitude":null,"DEPENDENCIA":"Privada","ATIVIDADE":"Em atividade","VÍNCULOS_PUBLICOS":"Não","MANTENEDOR_ESCOLA_PRIVADA":"Empresa do setor privado","PREDIO_ESCOLAR":"Próprio","LOCAL_ESCOLAR":"Outros","ABASTECIMENTO_AGUA":"Rede pública","ABASTECIMENTO_ENERGIA":"Rede pública","TAXA_DE_ACESSIBILIDADE":1,"DS_ENDERECO":"RUA JULIO PERICO","NU_ENDERECO":"50","DS_COMPLEMENTO":null,"NO_BAIRRO":"JARDIM DA COLINA","CO_CEP":17350226,"NU_DDD":14,"NU_TELEFONE":36445005,"ESGOTO":"Rede pública","TAXA_DE_INFRAESTRUTURA":2,"LISTA_INFRAESTRUTURAS":["Laboratório de Ciências","Laboratório de Informática"],"LISTA_PROFISSIONAIS":[],"IDEB_2023":null}
,
{"NO_MUNICIPIO":"Igaraçu do Tietê","NO_UF":"São Paulo","SG_UF":"SP","CO_DISTRITO":352000405,"NO_ENTIDADE":"JOSE PERASSOLI PREFEITO EMEIEF","CO_ENTIDADE":35228459,"longitude":-48.564564,"latitude":-22.522003,"DEPENDENCIA":"Municipal","ATIVIDADE":"Em atividade","VÍNCULOS_PUBLICOS":"Secretaria de Educação","MANTENEDOR_ESCOLA_PRIVADA":"Empresa do setor privado","PREDIO_ESCOLAR":"Próprio","LOCAL_ESCOLAR":"Outros","ABASTECIMENTO_AGUA":"Rede pública","ABASTECIMENTO_ENERGIA":"Rede pública","TAXA_DE_ACESSIBILIDADE":3,"DS_ENDERECO":"RUA JOAO ORTIGOZA","NU_ENDERECO":"200","DS_COMPLEMENTO":null,"NO_BAIRRO":"CONJUNTO HABITACIONAL IGARACU I","CO_CEP":17354150,"NU_DDD":14,"NU_TELEFONE":36441877,"ESGOTO":"Rede pública","TAXA_DE_INFRAESTRUTURA":0,"LISTA_INFRAESTRUTURAS":[],"LISTA_PROFISSIONAIS":["Técnicos de apoio a tecnologias educacionais"],"IDEB_2023":null}
,
{"NO_MUNICIPIO":"Igaraçu do Tietê","NO_UF":"São Paulo","SG_UF":"SP","CO_DISTRITO":352000405,"NO_ENTIDADE":"LUIZ PERES RODERO CEMEI","CO_ENTIDADE":35234436,"longitude":-48.567489,"latitude":-22.522668,"DEPENDENCIA":"Municipal","ATIVIDADE":"Em atividade","VÍNCULOS_PUBLICOS":"Secretaria de Educação","MANTENEDOR_ESCOLA_PRIVADA":"Empresa do setor privado","PREDIO_ESCOLAR":"Próprio","LOCAL_ESCOLAR":"Outros","ABASTECIMENTO_AGUA":"Rede pública","ABASTECIMENTO_ENERGIA":"Rede pública","TAXA_DE_ACESSIBILIDADE":0,"DS_ENDERECO":"RUA JOAO ORTIGOZA","NU_ENDERECO":"382","DS_COMPLEMENTO":null,"NO_BAIRRO":"CONJUNTO HABITACIONAL IGARACU I","CO_CEP":17354150,"NU_DDD":14,"NU_TELEFONE":36445529,"ESGOTO":"Rede pública","TAXA_DE_INFRAESTRUTURA":0,"LISTA_INFRAESTRUTURAS":[],"LISTA_PROFISSIONAIS":[],"IDEB_2023":null}
,
{"NO_MUNICIPIO":"Igaraçu do Tietê","NO_UF":"São Paulo","SG_UF":"SP","CO_DISTRITO":352000405,"NO_ENTIDADE":"MARIA HELENA FRANCISCO FRAGA CEMEI","CO_ENTIDADE":35234448,"longitude":-48.566172,"latitude":-22.515362,"DEPENDENCIA":"Municipal","ATIVIDADE":"Em atividade","VÍNCULOS_PUBLICOS":"Secretaria de Educação","MANTENEDOR_ESCOLA_PRIVADA":"Empresa do setor privado","PREDIO_ESCOLAR":"Próprio","LOCAL_ESCOLAR":"Outros","ABASTECIMENTO_AGUA":"Rede pública","ABASTECIMENTO_ENERGIA":"Rede pública","TAXA_DE_ACESSIBILIDADE":2,"DS_ENDERECO":"RUA MARIO LEMOS DE AZEVEDO","NU_ENDERECO":"570","DS_COMPLEMENTO":null,"NO_BAIRRO":"JARDIM ALTOS DO IGARACU","CO_CEP":17352410,"NU_DDD":14,"NU_TELEFONE":36445546,"ESGOTO":"Rede pública","TAXA_DE_INFRAESTRUTURA":0,"LISTA_INFRAESTRUTURAS":[],"LISTA_PROFISSIONAIS":[],"IDEB_2023":null}
,
{"NO_MUNICIPIO":"Igaraçu do Tietê","NO_UF":"São Paulo","SG_UF":"SP","CO_DISTRITO":352000405,"NO_ENTIDADE":"JOAO TUSCHI EM","CO_ENTIDADE":35436872,"longitude":-48.552032,"latitude":-22.517945,"DEPENDENCIA":"Municipal","ATIVIDADE":"Em atividade","VÍNCULOS_PUBLICOS":"Secretaria de Educação","MANTENEDOR_ESCOLA_PRIVADA":"Empresa do setor privado","PREDIO_ESCOLAR":"Próprio","LOCAL_ESCOLAR":"Prédio compartilhado com outra escola","ABASTECIMENTO_AGUA":"Rede pública","ABASTECIMENTO_ENERGIA":"Rede pública","TAXA_DE_ACESSIBILIDADE":4,"DS_ENDERECO":"RUA VIRGILIO TUSCHI","NU_ENDERECO":"200","DS_COMPLEMENTO":null,"NO_BAIRRO":"CONJUNTO HABITACIONAL IGARACU I","CO_CEP":17354138,"NU_DDD":14,"NU_TELEFONE":36448701,"ESGOTO":"Rede pública","TAXA_DE_INFRAESTRUTURA":2,"LISTA_INFRAESTRUTURAS":["Laboratório de Informática","Quadra de Esportes"],"LISTA_PROFISSIONAIS":["Psicólogo"],"IDEB_2023":null}
,
{"NO_MUNICIPIO":"Igaraçu do Tietê","NO_UF":"São Paulo","SG_UF":"SP","CO_DISTRITO":352000405,"NO_ENTIDADE":"ODYNIR MAGANHA EM","CO_ENTIDADE":35436884,"longitude":-48.551025,"latitude":-22.517683,"DEPENDENCIA":"Municipal","ATIVIDADE":"Em atividade","VÍNCULOS_PUBLICOS":"Secretaria de Educação","MANTENEDOR_ESCOLA_PRIVADA":"Empresa do setor privado","PREDIO_ESCOLAR":"Cedido","LOCAL_ESCOLAR":"Outros","ABASTECIMENTO_AGUA":"Rede pública","ABASTECIMENTO_ENERGIA":"Rede pública","TAXA_DE_ACESSIBILIDADE":2,"DS_ENDERECO":"RUA ALVINO MOREIRA","NU_ENDERECO":"760","DS_COMPLEMENTO":null,"NO_BAIRRO":"CECAP","CO_CEP":17357218,"NU_DDD":14,"NU_TELEFONE":36448702,"ESGOTO":"Rede pública","TAXA_DE_INFRAESTRUTURA":1,"LISTA_INFRAESTRUTURAS":["Quadra de Esportes"],"LISTA_PROFISSIONAIS":[],"IDEB_2023":null}
,
{"NO_MUNICIPIO":"Igaraçu do Tietê","NO_UF":"São Paulo","SG_UF":"SP","CO_DISTRITO":352000405,"NO_ENTIDADE":"ANGELO DOMEZI PREFEITO EM","CO_ENTIDADE":35436896,"longitude":-48.558392,"latitude":-22.511316,"DEPENDENCIA":"Municipal","ATIVIDADE":"Em atividade","VÍNCULOS_PUBLICOS":"Secretaria de Educação","MANTENEDOR_ESCOLA_PRIVADA":"Empresa do setor privado","PREDIO_ESCOLAR":"Cedido","LOCAL_ESCOLAR":"Outros","ABASTECIMENTO_AGUA":"Rede pública","ABASTECIMENTO_ENERGIA":"Rede pública","TAXA_DE_ACESSIBILIDADE":4,"DS_ENDERECO":"RUA JULIO VIEIRA","NU_ENDERECO":"395","DS_COMPLEMENTO":null,"NO_BAIRRO":"IGARACU DO TIETE","CO_CEP":17350017,"NU_DDD":14,"NU_TELEFONE":36441666,"ESGOTO":"Rede pública","TAXA_DE_INFRAESTRUTURA":2,"LISTA_INFRAESTRUTURAS":["Laboratório de Informática","Quadra de Esportes"],"LISTA_PROFISSIONAIS":["Psicólogo","Técnicos de apoio a tecnologias educacionais"],"IDEB_2023":null}
,
{"NO_MUNICIPIO":"Igaraçu do Tietê","NO_UF":"São Paulo","SG_UF":"SP","CO_DISTRITO":352000405,"NO_ENTIDADE":"CONCEICAO BONANI GAMA CEMEI","CO_ENTIDADE":35444455,"longitude":-48.560162,"latitude":-22.526406,"DEPENDENCIA":"Municipal","ATIVIDADE":"Em atividade","VÍNCULOS_PUBLICOS":"Secretaria de Educação","MANTENEDOR_ESCOLA_PRIVADA":"Empresa do setor privado","PREDIO_ESCOLAR":"Próprio","LOCAL_ESCOLAR":"Outros","ABASTECIMENTO_AGUA":"Rede pública","ABASTECIMENTO_ENERGIA":"Rede pública","TAXA_DE_ACESSIBILIDADE":1,"DS_ENDERECO":"RUA MARIA SALVE FERRAZ","NU_ENDERECO":"20","DS_COMPLEMENTO":null,"NO_BAIRRO":"CONJUNTO HABITACIONAL JOAO CAPELAZZO","CO_CEP":17354074,"NU_DDD":14,"NU_TELEFONE":36445542,"ESGOTO":"Rede pública","TAXA_DE_INFRAESTRUTURA":0,"LISTA_INFRAESTRUTURAS":[],"LISTA_PROFISSIONAIS":[],"IDEB_2023":null}
,
{"NO_MUNICIPIO":"Igaraçu do Tietê","NO_UF":"São Paulo","SG_UF":"SP","CO_DISTRITO":352000405,"NO_ENTIDADE":"CAMILO SAHADE","CO_ENTIDADE":35909282,"longitude":-48.566401,"latitude":-22.521871,"DEPENDENCIA":"Estadual","ATIVIDADE":"Em atividade","VÍNCULOS_PUBLICOS":"Secretaria de Educação","MANTENEDOR_ESCOLA_PRIVADA":"Empresa do setor privado","PREDIO_ESCOLAR":"Próprio","LOCAL_ESCOLAR":"Outros","ABASTECIMENTO_AGUA":"Rede pública","ABASTECIMENTO_ENERGIA":"Rede pública","TAXA_DE_ACESSIBILIDADE":0,"DS_ENDERECO":"RUA RICIERI ZERLIN","NU_ENDERECO":"395","DS_COMPLEMENTO":null,"NO_BAIRRO":"CONJUNTO HABITACIONAL IGARACU I","CO_CEP":17354148,"NU_DDD":14,"NU_TELEFONE":36448700,"ESGOTO":"Rede pública","TAXA_DE_INFRAESTRUTURA":2,"LISTA_INFRAESTRUTURAS":["Laboratório de Informática","Quadra de Esportes"],"LISTA_PROFISSIONAIS":[],"IDEB_2023":"4,2"}
,
{"NO_MUNICIPIO":"Igaraçu do Tietê","NO_UF":"São Paulo","SG_UF":"SP","CO_DISTRITO":352000405,"NO_ENTIDADE":"ODYNIR MAGANHA","CO_ENTIDADE":35913881,"longitude":null,"latitude":null,"DEPENDENCIA":"Estadual","ATIVIDADE":"Paralisada","VÍNCULOS_PUBLICOS":"Não","MANTENEDOR_ESCOLA_PRIVADA":"Empresa do setor privado","PREDIO_ESCOLAR":"Indefinido","LOCAL_ESCOLAR":"Outros","ABASTECIMENTO_AGUA":"Não há abastecimento de água","ABASTECIMENTO_ENERGIA":"Não há energia elétrica","TAXA_DE_ACESSIBILIDADE":0,"DS_ENDERECO":"RUA ALVINO MOREIRA","NU_ENDERECO":null,"DS_COMPLEMENTO":null,"NO_BAIRRO":"NUCLEO HABITACIONAL COMENDADOR ORLANDO CHESINI OME","CO_CEP":17357220,"NU_DDD":14,"NU_TELEFONE":36448702,"ESGOTO":"Não há tratamento de esgoto","TAXA_DE_INFRAESTRUTURA":0,"LISTA_INFRAESTRUTURAS":[],"LISTA_PROFISSIONAIS":[],"IDEB_2023":null}
,
{"NO_MUNICIPIO":"Igaraçu do Tietê","NO_UF":"São Paulo","SG_UF":"SP","CO_DISTRITO":352000405,"NO_ENTIDADE":"JOAO TUSCHI","CO_ENTIDADE":35917679,"longitude":null,"latitude":null,"DEPENDENCIA":"Estadual","ATIVIDADE":"Paralisada","VÍNCULOS_PUBLICOS":"Não","MANTENEDOR_ESCOLA_PRIVADA":"Empresa do setor privado","PREDIO_ESCOLAR":"Indefinido","LOCAL_ESCOLAR":"Outros","ABASTECIMENTO_AGUA":"Não há abastecimento de água","ABASTECIMENTO_ENERGIA":"Não há energia elétrica","TAXA_DE_ACESSIBILIDADE":0,"DS_ENDERECO":"RUA VIRGILIO TUSCHI","NU_ENDERECO":"200","DS_COMPLEMENTO":"RUA","NO_BAIRRO":"COHAB","CO_CEP":17354138,"NU_DDD":14,"NU_TELEFONE":36448701,"ESGOTO":"Não há tratamento de esgoto","TAXA_DE_INFRAESTRUTURA":0,"LISTA_INFRAESTRUTURAS":[],"LISTA_PROFISSIONAIS":[],"IDEB_2023":null}
,
{"NO_MUNICIPIO":"Igaraçu do Tietê","NO_UF":"São Paulo","SG_UF":"SP","CO_DISTRITO":352000405,"NO_ENTIDADE":"CEL JTO A EE JOSE CONTI","CO_ENTIDADE":35985831,"longitude":-48.56242,"latitude":-22.510167,"DEPENDENCIA":"Estadual","ATIVIDADE":"Em atividade","VÍNCULOS_PUBLICOS":"Secretaria de Educação","MANTENEDOR_ESCOLA_PRIVADA":"Empresa do setor privado","PREDIO_ESCOLAR":"Próprio","LOCAL_ESCOLAR":"Prédio compartilhado com outra escola","ABASTECIMENTO_AGUA":"Rede pública","ABASTECIMENTO_ENERGIA":"Rede pública","TAXA_DE_ACESSIBILIDADE":0,"DS_ENDERECO":"AVENIDA JOSE MICHEL MUCARE","NU_ENDERECO":"801","DS_COMPLEMENTO":null,"NO_BAIRRO":"JARDIM NOVO ESTILO","CO_CEP":17350298,"NU_DDD":14,"NU_TELEFONE":36441777,"ESGOTO":"Rede pública","TAXA_DE_INFRAESTRUTURA":1,"LISTA_INFRAESTRUTURAS":["Laboratório de Informática"],"LISTA_PROFISSIONAIS":[],"IDEB_2023":null}
 ] }